README.rst
setup.cfg
setup.py
peek_doc_admin/__init__.py
peek_doc_admin/build_html_docs.sh
peek_doc_admin/build_latex_docs.sh
peek_doc_admin/conf.py
peek_doc_admin/index.rst
peek_doc_admin/watch_docs.sh
peek_doc_admin/welcome.rst
peek_doc_admin.egg-info/PKG-INFO
peek_doc_admin.egg-info/SOURCES.txt
peek_doc_admin.egg-info/dependency_links.txt
peek_doc_admin.egg-info/not-zip-safe
peek_doc_admin.egg-info/requires.txt
peek_doc_admin.egg-info/top_level.txt
peek_doc_admin/_static/.gitkeep
peek_doc_admin/_static/fonts/fontawesome-webfont.woff2